tk_core/aws/secrets.py
tk_core/common/__init__.py
tk_core/common/dates.py
tk_core/common/de_service.py
tk_core/common/dictionary.py
tk_core/common/files.py
tk_core/common/hasher.py
tk_core/common/pandas.py
tk_core/common/s3.py
tk_core/common/timeout.py
tk_core/core/__init__.py
tk_core/core/base_request.py
tk_core/core/batch_request.py
tk_core/core/memory.py
tk_core/core/models.py
tk_core/core/request_id.py
tk_core/core/test_batch_request.py
tk_core/core/tk_redis.py
tk_core/core/async_module/__init__.py
tk_core/core/async_module/async_messaging.py
tk_core/core/async_module/generic_request_processor.py
tk_core/core/async_module/models.py
tk_core/gp/models.py
tk_core/page_restructuring/__init__.py
tk_core/page_restructuring/batch_page_restructuring.py
tk_core/page_restructuring/models.py
tk_core/page_restructuring/utils/html_extraction.py
tk_core/page_restructuring/utils/link_extraction.py
tk_core/page_restructuring/utils/page_extraction.py
tk_core/page_scrape/batch_page_scrape.py
tk_core/page_scrape/constants.py
tk_core/page_scrape/models.py
tk_core/page_scrape/scraping_bee.py
tk_core/prefect/__init__.py
tk_core/prefect/prefect_api.py
tk_core/serp_api/__init__.py
tk_core/serp_api/base.py
tk_core/serp_api/batch_serp.py
tk_core/serp_api/models.py
tk_core/serp_api/serp.py
tk_core/serp_api/trend.py
tk_core/serp_api/util.py
tk_core/snowkeet/__init__.py
tk_core/snowkeet/error_wrapper.py
tk_core/snowkeet/snow_logger.py
tk_core/snowkeet/snowkeet.py
tk_core/timing/__init__.py
tk_core/timing/time.py
tk_core/urls/__init__.py
tk_core/urls/normalizer.py
tk_core-1.5.0.dist-info/METADATA
tk_core-1.5.0.dist-info/WHEEL
tk_core-1.5.0.dist-info/top_level.txt
tk_core-1.5.0.dist-info/RECORD
