Metadata-Version: 2.4
Name: tk_core
Version: 1.5.0
Summary: Centralized core functionality for Terakeet SD, DS, DE, etc.
Requires-Dist: boto3
Requires-Dist: botocore
Requires-Dist: pandas==2.1.4
Requires-Dist: pydantic
Requires-Dist: python-dotenv
Requires-Dist: scrapingbee
Requires-Dist: serpapi
Requires-Dist: snowflake-connector-python[pandas]
Requires-Dist: snowflake-snowpark-python[pandas]
Requires-Dist: ujson
Requires-Dist: redis==5.3.0
Requires-Dist: retry
Requires-Dist: rich
Requires-Dist: trafilatura==1.7.0
Requires-Dist: extruct
Requires-Dist: beautifulsoup4
Requires-Dist: newspaper3k
Requires-Dist: opengraph
Requires-Dist: jsonschema
Requires-Dist: psutil
Requires-Dist: tqdm
Requires-Dist: lxml==5.1.0
Provides-Extra: dev
Requires-Dist: pre-commit; extra == "dev"
Requires-Dist: ruff; extra == "dev"
Requires-Dist: build; extra == "dev"
Requires-Dist: twine; extra == "dev"
Requires-Dist: pytest; extra == "dev"
Requires-Dist: pytest-asyncio; extra == "dev"
Requires-Dist: pytest-cov; extra == "dev"
Requires-Dist: pytest-mock; extra == "dev"
Requires-Dist: moto; extra == "dev"
Requires-Dist: requests-mock; extra == "dev"
